serializer_data/__init__.py
serializer_data/serializable.py
serializer_data/serializer.py
serializer_data-2.0.0.dist-info/LICENSE
serializer_data-2.0.0.dist-info/METADATA
serializer_data-2.0.0.dist-info/WHEEL
serializer_data-2.0.0.dist-info/top_level.txt
serializer_data-2.0.0.dist-info/RECORD
