Metadata-Version: 2.1
Name: serializer-data
Version: 2.0.0
Summary: serialize and deserialize objects
Home-page: https://github.com/Antonino0704
Author: Antonino Buscarino
Author-email: fifaanto17@gmail.com
Project-URL: Bug Tracker, https://github.com/Antonino0704/serializer_data
Classifier: Programming Language :: Python :: 3
Classifier: License :: OSI Approved :: GNU General Public License v3 or later (GPLv3+)
Classifier: Operating System :: OS Independent
Requires-Python: >=3.8
License-File: LICENSE
